fastapi_auth/__init__.py
fastapi_auth/_mongodb_access.py
fastapi_auth/_mysql_access.py
fastapi_auth/_postgres_access.py
fastapi_auth/_security_secret.py
fastapi_auth/_sqlite_access.py
fastapi_auth/endpoints.py
fastapi_auth/security_api_key.py
fastapi_auth2-1.0.6.dist-info/LICENSE
fastapi_auth2-1.0.6.dist-info/METADATA
fastapi_auth2-1.0.6.dist-info/WHEEL
fastapi_auth2-1.0.6.dist-info/top_level.txt
fastapi_auth2-1.0.6.dist-info/RECORD
