Metadata-Version: 2.1
Name: fastapi-auth2
Version: 1.0.6
Summary: FastAPI Auth is a package that provides authentication based API security with FastAPI and Postgres Database or Sqlite3 Database
Home-page: https://nneji123.github.io/fastapi_auth/
Author: Ifeanyi Nneji
Author-email: ifeanyinneji@gmail.com
License: MIT
Project-URL: Funding, https://github.com/sponsors/Nneji123
Project-URL: Source, https://github.com/Nneji123/fastapi_auth
Classifier: Development Status :: 5 - Production/Stable
Classifier: Environment :: Console
Classifier: Intended Audience :: Developers
Classifier: License :: OSI Approved :: MIT License
Classifier: Operating System :: OS Independent
Classifier: Natural Language :: English
Classifier: Topic :: Internet :: WWW/HTTP
Classifier: Topic :: Software Development :: Code Generators
Classifier: Programming Language :: Python :: 3
Classifier: Programming Language :: Python :: 3.7
Classifier: Programming Language :: Python :: 3.8
Classifier: Programming Language :: Python :: 3.9
Classifier: Programming Language :: Python :: 3.10
Requires-Python: >=3.7
License-File: LICENSE
Requires-Dist: passwordgenerator (>=1.5.1)
Requires-Dist: fastapi (>=0.70)
Requires-Dist: urllib3 (>=1.26.12)
Requires-Dist: psycopg2 (>=2.9.5)
Requires-Dist: bcrypt (>=4.0.1)
Requires-Dist: email-validator (>=1.3.0)
Requires-Dist: pymysql (>=1.0.2)
Requires-Dist: uvicorn (>=0.18.3)
Requires-Dist: pymongo (>=4.0.0)
Requires-Dist: python-dotenv (>=0.20.0)
